src/__init__.py
src/config.json
src/logger.py
src/main.py
src/html/favicon.ico
src/html/index.html
betterbio-1.0.3.dist-info/METADATA
betterbio-1.0.3.dist-info/WHEEL
betterbio-1.0.3.dist-info/entry_points.txt
betterbio-1.0.3.dist-info/RECORD
