Metadata-Version: 2.4
Name: BetterBio
Version: 1.0.3
Summary: A self-hosted links website based on the style of a Discord profile.
Requires-Python: >=3.10
Requires-Dist: discord-py>=2.6.4
Requires-Dist: flask>=3.1.2
